chopcal-0.3.1.dist-info/METADATA
chopcal-0.3.1.dist-info/RECORD
chopcal-0.3.1.dist-info/entry_points.txt
chopcal-0.3.1.dist-info/WHEEL
chopcal-0.3.1.dist-info/licenses/LICENSE
chopcal/_chopper_lib_impl.pypy39-pp73-x86_64-linux-gnu.so
chopcal/__init__.py
chopcal/_chopcal_impl.pypy39-pp73-x86_64-linux-gnu.so
