Metadata-Version: 2.1
Name: chopcal
Version: 0.3.1
Summary: Provides the results of chopper calculations from McStas instruments
Author-Email: Gregory Tucker <gregory.tucker@ess.eu>
Classifier: License :: OSI Approved :: BSD License
Project-URL: Homepage, https://github.com/g5t/chopper-calculations
Requires-Python: >=3.8
